cqrcode/__init__.py
cqrcode/app/__init__.py
cqrcode/app/__pycache__/__init__.cpython-35.pyc
cqrcode/app/make_qrcode/QRcode.py
cqrcode/app/make_qrcode/__init__.py
cqrcode/app/make_qrcode/alpha2bit.py
cqrcode/app/make_qrcode/create_cylinder_qrcode_main.py
cqrcode/app/make_qrcode/expand_figure.py
cqrcode/app/make_qrcode/prepare_moudle.py
cqrcode/app/make_qrcode/__pycache__/QRcode.cpython-35.pyc
cqrcode/app/make_qrcode/__pycache__/__init__.cpython-35.pyc
cqrcode/app/make_qrcode/__pycache__/alpha2bit.cpython-35.pyc
cqrcode/app/make_qrcode/__pycache__/create_cylinder_qrcode_main.cpython-35.pyc
cqrcode/app/make_qrcode/__pycache__/expand_figure.cpython-35.pyc
cqrcode/app/make_qrcode/__pycache__/prepare_moudle.cpython-35.pyc
cqrcode/app/scan_qrcode/__init__.py
cqrcode/app/scan_qrcode/camera.py
cqrcode/app/scan_qrcode/scan_cylinder_qrcode_main.py
cqrcode/app/scan_qrcode/__pycache__/__init__.cpython-35.pyc
cqrcode/app/scan_qrcode/__pycache__/scan_cylinder_qrcode_main.cpython-35.pyc
cqrcode/static/__init__.py
cqrcode/static/_blank.png
cqrcode/static/_static_data.py
cqrcode/static/__pycache__/__init__.cpython-35.pyc
cqrcode/static/__pycache__/_static_data.cpython-35.pyc
cqrcode/static/__pycache__/static_data.cpython-35.pyc
cqrcode/view/GUI_view.py
cqrcode/view/GUI_welcome.py
cqrcode/view/__init__.py
cqrcode/view/__pycache__/GUI_view.cpython-35.pyc
cqrcode/view/__pycache__/GUI_welcome.cpython-35.pyc
cqrcode/view/__pycache__/__init__.cpython-35.pyc
cqrcode-1.21.dist-info/METADATA
cqrcode-1.21.dist-info/WHEEL
cqrcode-1.21.dist-info/top_level.txt
cqrcode-1.21.dist-info/RECORD
