Metadata-Version: 2.1
Name: cqrcode
Version: 1.21
Summary: Generate a QR code that can adapt to the cylinder
Home-page: https://pypi.org/project/cqrcode/
Author: jiaming
Author-email: 837357785@qq.com
License: MIT
Keywords: cylinder qrcode
Platform: UNKNOWN
Classifier: Natural Language :: Chinese (Simplified)
Classifier: Development Status :: 3 - Alpha
Classifier: Operating System :: OS Independent
Classifier: Programming Language :: Python
Classifier: Programming Language :: Python :: 3.4
Classifier: Programming Language :: Python :: 3.5
Classifier: Programming Language :: Python :: 3.6
Classifier: Programming Language :: Python :: 3.7
Classifier: Programming Language :: Python :: 3.8
Classifier: License :: OSI Approved :: MIT License
Classifier: Topic :: Utilities
Requires-Dist: Pillow (>=6.1.0)
Requires-Dist: pyzbar (>=0.1.8)
Requires-Dist: qrcode (>=6.1)
Requires-Dist: matplotlib (>=3.0.3)
Requires-Dist: opencv-python (>=4.1.1.26)
